{
	"MaxHp": 30,
	"Hp": 30,
	"MoveSpeed": 300.0,
	"MoveSpeedOrigin": 400.0,
	"MoveSpeedEvade": 600.0,
	"MaxSightDistance": 400.0,
	"SightAngle": 90.0,
	"MaxRoamDistance": 900.0,
	"MaxChaseDistance": 2000.0,
	"AttackRange": 150.0,
	"AtkAngle": 20.0,
	"AttackInterval": 0.6,
	"KnockdownResist": 6,
	"KnockdownPointResetTime": 5.0,
	"KnockbackResist": 5,
	"EvadeDistance": 300.0,
	"EvadeProbability": 20.0,
	"Attack1Probability": 80.0,
	"Attack2Probability": 0.0,
	"Attack3Probability": 0.0,
	"AttackPowerMin": 3,
	"AttackPowerMax": 4,
	"Attack2PowerMin": 0,
	"Attack2PowerMax": 0,
	"Attack3PowerMin": 0,
	"Attack3PowerMax": 0,
	"AttackKnockdownPower": 3,
	"AttackA_BProb": 0.6,
	"AttackA_CProb": 0.4,
	"AttackB_BProb": 0.5,
	"AttackB_CProb": 0.5,
	"AttackC_BProb": 0.5,
	"AttackC_CProb": 0.5,
	"AttackA_ATime": 1.0,
	"AttackA_BTime": 1.0,
	"AttackA_CTime": 1.0,
	"AttackB_ATime": 1.0,
	"AttackB_BTime": 1.0,
	"AttackB_CTime": 1.0,
	"AttackC_ATime": 1.0,
	"AttackC_BTime": 1.0,
	"AttackC_CTime": 1.0,
	"Attack1AMoveSpd": 300.0,
	"Attack1BMoveSpd": 300.0,
	"Attack1CMoveSpd": 300.0,
	"Attack2AMoveSpd": 300.0,
	"Attack2BMoveSpd": 300.0,
	"Attack2CMoveSpd": 300.0,
	"Attack3AMoveSpd": 300.0,
	"Attack3BMoveSpd": 300.0,
	"Attack3CMoveSpd": 300.0,
	"Attack1AMoveDist": 30.0,
	"Attack1BMoveDist": 30.0,
	"Attack1CMoveDist": 30.0,
	"Attack2AMoveDist": 30.0,
	"Attack2BMoveDist": 30.0,
	"Attack2CMoveDist": 30.0,
	"Attack3AMoveDist": 30.0,
	"Attack3BMoveDist": 30.0,
	"Attack3CMoveDist": 30.0	
}